__init__.py
fai/__init__.py
fai/agent.py
fai/auxiliary.py
fai/cache.py
fai/catch.py
fai/chat.py
fai/extract.py
fai/loop.py
fai/parallel.py
fai/prompts.py
fai/sequential.py
fai/switch.py
fai/tests.py
fai/transform.py
fun_ai_lib-0.2.0.dist-info/licenses/LICENSE
fun_ai_lib-0.2.0.dist-info/METADATA
fun_ai_lib-0.2.0.dist-info/WHEEL
fun_ai_lib-0.2.0.dist-info/top_level.txt
fun_ai_lib-0.2.0.dist-info/RECORD
