Metadata-Version: 2.4
Name: fun-ai-lib
Version: 0.2.0
Summary: A backend-agnostic, modular AI orchestration framework for building LLM-powered pipelines with functional building blocks
Author-email: Greg Zozulin <gzozulin@gmail.com>
License: Apache-2.0
Requires-Python: >=3.8
License-File: LICENSE
Dynamic: license-file
